IntrinsicAnalysis/__init__.py
IntrinsicAnalysis/analyse.py
IntrinsicAnalysis/clustering/AC_model.py
IntrinsicAnalysis/clustering/__init__.py
IntrinsicAnalysis/clustering/main.py
IntrinsicAnalysis/feature_extractors/__init__.py
IntrinsicAnalysis/feature_extractors/char_general.py
IntrinsicAnalysis/feature_extractors/char_punct.py
IntrinsicAnalysis/feature_extractors/computation.py
IntrinsicAnalysis/feature_extractors/readability.py
IntrinsicAnalysis/feature_extractors/sent_general.py
IntrinsicAnalysis/feature_extractors/sent_morph.py
IntrinsicAnalysis/feature_extractors/sent_syntactic.py
IntrinsicAnalysis/feature_extractors/utils.py
IntrinsicAnalysis/feature_extractors/word_abbrev.py
IntrinsicAnalysis/feature_extractors/word_general.py
IntrinsicAnalysis/feature_extractors/word_ngrams.py
IntrinsicAnalysis/feature_extractors/word_numbers.py
IntrinsicAnalysis/feature_extractors/external_data/abbrevs.txt
IntrinsicAnalysis/feature_extractors/external_data/bigrams_with_idf.txt
IntrinsicAnalysis/feature_extractors/external_data/cardinal_numbers.txt
IntrinsicAnalysis/feature_extractors/external_data/common_abbrevs.txt
IntrinsicAnalysis/feature_extractors/external_data/common_pos_bigrams.txt
IntrinsicAnalysis/feature_extractors/external_data/common_pos_trigrams.txt
IntrinsicAnalysis/feature_extractors/external_data/dependency_labels.txt
IntrinsicAnalysis/feature_extractors/external_data/jargon_words.txt
IntrinsicAnalysis/feature_extractors/external_data/months.txt
IntrinsicAnalysis/feature_extractors/external_data/ordinal_numbers.txt
IntrinsicAnalysis/feature_extractors/external_data/pos_labels.txt
IntrinsicAnalysis/feature_extractors/external_data/prefixes.txt
IntrinsicAnalysis/feature_extractors/external_data/puncts.txt
IntrinsicAnalysis/feature_extractors/external_data/suffixes.txt
IntrinsicAnalysis/feature_extractors/external_data/syllables.txt
IntrinsicAnalysis/feature_extractors/external_data/trigrams_with_idf.txt
IntrinsicAnalysis-0.0.3.dist-info/LICENSE
IntrinsicAnalysis-0.0.3.dist-info/METADATA
IntrinsicAnalysis-0.0.3.dist-info/WHEEL
IntrinsicAnalysis-0.0.3.dist-info/top_level.txt
IntrinsicAnalysis-0.0.3.dist-info/RECORD
