Metadata-Version: 2.1
Name: IntrinsicAnalysis
Version: 0.0.3
Summary: Intrinsic analysis package
Home-page: https://github.com/arianasatryan/IntrinsicAnalysis.git
Author: Ariana Asatryan, Tsolak Ghukasyan, Yeva Yeshilbashian
License: UNKNOWN
Platform: UNKNOWN
Classifier: Programming Language :: Python :: 3
Classifier: Operating System :: POSIX :: Linux
Requires-Dist: stanza (>=1.0.1")
Requires-Dist: spacy-udpipe (>=0.3.1)
Requires-Dist: nltk
Requires-Dist: scikit-learn
